free_apis_llm_cascade/__init__.py
free_apis_llm_cascade/cascade.py
free_apis_llm_cascade/model_registry.json
free_apis_llm_cascade/providers/__init__.py
free_apis_llm_cascade/providers/googleai.py
free_apis_llm_cascade/providers/groq.py
free_apis_llm_cascade/providers/openrouter.py
free_apis_llm_cascade/providers/sambanova.py
free_apis_llm_cascade/utils/errors.py
free_apis_llm_cascade-0.2.1.dist-info/LICENSE.txt
free_apis_llm_cascade-0.2.1.dist-info/METADATA
free_apis_llm_cascade-0.2.1.dist-info/WHEEL
free_apis_llm_cascade-0.2.1.dist-info/top_level.txt
free_apis_llm_cascade-0.2.1.dist-info/RECORD
