Metadata-Version: 2.2
Name: free-apis-llm-cascade
Version: 0.2.1
Summary: Free API-based LLM Cascading
Author: Henry Michaelson
License: MIT
Project-URL: Homepage, https://github.com/h-michaelson20/open-source-free-cascader
Project-URL: Repository, https://github.com/h-michaelson20/open-source-free-cascader.git
Classifier: License :: OSI Approved :: MIT License
Requires-Python: >=3.8
License-File: LICENSE.txt
Requires-Dist: scikit-learn
Requires-Dist: python-dotenv
Requires-Dist: google-generativeai
Requires-Dist: groq
Requires-Dist: requests
Requires-Dist: openai
Provides-Extra: test
Requires-Dist: pytest; extra == "test"
Requires-Dist: mkdocs; extra == "test"
